cnmaps/__init__.py
cnmaps/names.py
cnmaps/regions.py
cnmaps/sample.py
cnmaps/data/__init__.py
cnmaps/data/geojson.min/default/100000.geojson
cnmaps/data/geojson.min/default/110000.geojson
cnmaps/data/geojson.min/default/120000.geojson
cnmaps/data/geojson.min/default/130000.geojson
cnmaps/data/geojson.min/default/140000.geojson
cnmaps/data/geojson.min/default/150000.geojson
cnmaps/data/geojson.min/default/210000.geojson
cnmaps/data/geojson.min/default/220000.geojson
cnmaps/data/geojson.min/default/230000.geojson
cnmaps/data/geojson.min/default/310000.geojson
cnmaps/data/geojson.min/default/320000.geojson
cnmaps/data/geojson.min/default/330000.geojson
cnmaps/data/geojson.min/default/340000.geojson
cnmaps/data/geojson.min/default/350000.geojson
cnmaps/data/geojson.min/default/360000.geojson
cnmaps/data/geojson.min/default/370000.geojson
cnmaps/data/geojson.min/default/410000.geojson
cnmaps/data/geojson.min/default/420000.geojson
cnmaps/data/geojson.min/default/430000.geojson
cnmaps/data/geojson.min/default/440000.geojson
cnmaps/data/geojson.min/default/450000.geojson
cnmaps/data/geojson.min/default/460000.geojson
cnmaps/data/geojson.min/default/500000.geojson
cnmaps/data/geojson.min/default/510000.geojson
cnmaps/data/geojson.min/default/520000.geojson
cnmaps/data/geojson.min/default/530000.geojson
cnmaps/data/geojson.min/default/540000.geojson
cnmaps/data/geojson.min/default/610000.geojson
cnmaps/data/geojson.min/default/620000.geojson
cnmaps/data/geojson.min/default/630000.geojson
cnmaps/data/geojson.min/default/640000.geojson
cnmaps/data/geojson.min/default/650000.geojson
cnmaps/data/geojson.min/default/710000.geojson
cnmaps/data/geojson.min/default/810000.geojson
cnmaps/data/geojson.min/default/820000.geojson
cnmaps/data/geojson.min/default/Anhui.geojson
cnmaps/data/geojson.min/default/Beijing.geojson
cnmaps/data/geojson.min/default/ChinaLand.geojson
cnmaps/data/geojson.min/default/ChinaLand2.geojson
cnmaps/data/geojson.min/default/Chongqing.geojson
cnmaps-0.2.1.dist-info/LICENSE
cnmaps-0.2.1.dist-info/METADATA
cnmaps-0.2.1.dist-info/WHEEL
cnmaps-0.2.1.dist-info/top_level.txt
cnmaps-0.2.1.dist-info/RECORD
