Metadata-Version: 2.1
Name: cnmaps
Version: 0.2.1
Summary: A python package to draw china maps more easily
Home-page: https://github.com/Clarmy/cnmaps
Author: Wentao Li
Author-email: clarmylee92510@gmail.com
License: UNKNOWN
Platform: UNKNOWN
Classifier: Programming Language :: Python :: 3
Requires-Python: >=3.6
License-File: LICENSE
Requires-Dist: matplotlib
Requires-Dist: Cartopy (>=0.19.0)
Requires-Dist: Shapely
Requires-Dist: numpy
Requires-Dist: netCDF4
